xl/__init__.py
xl-0.0.5.dist-info/licenses/LICENSE
xl-0.0.5.dist-info/METADATA
xl-0.0.5.dist-info/WHEEL
xl-0.0.5.dist-info/top_level.txt
xl-0.0.5.dist-info/RECORD
