Metadata-Version: 2.4
Name: xl
Version: 0.0.5
Summary: Parsing google results
Home-page: https://github.com/t-c-w/xl
Author: Thor Whalen
License: apache-2.0
Platform: any
License-File: LICENSE
Dynamic: license-file
